delcechfiltr/__init__.py
delcechfiltr/dgms.py
delcechfiltr/tetra.py
delcechfiltr/tri.py
delcechfiltr/cpp/__init__.py
delcechfiltr/cpp/binding.cp38-win_amd64.pyd
delcechfiltr-1.0.1.dist-info/LICENSE.txt
delcechfiltr-1.0.1.dist-info/METADATA
delcechfiltr-1.0.1.dist-info/WHEEL
delcechfiltr-1.0.1.dist-info/top_level.txt
delcechfiltr-1.0.1.dist-info/RECORD
