Metadata-Version: 2.1
Name: delcechfiltr
Version: 1.0.1
Summary: Radius parameters of simplices in Delaunay-Cech filtration of 2D and 3D points.
Home-page: https://github.com/gbeltramo/delcechfiltr
Author: Gabriele Beltramo
License: GPLv3
Keywords: Delaunay triangulation,Cech complexes,radius parameter
Platform: UNKNOWN
Requires-Python: >=3.1
Requires-Dist: numpy
Requires-Dist: scipy
